pyibis_ami-8.0.0.dist-info/licenses/LICENSE
pyibisami/IBIS_AMI_Checker.ipynb
pyibisami/IBIS_AMI_Tester.ipynb
pyibisami/__init__.py
pyibisami/__main__.py
pyibisami/common.py
pyibisami/ami/__init__.py
pyibisami/ami/config.py
pyibisami/ami/generic.ami.em
pyibisami/ami/generic.ibs.em
pyibisami/ami/model.py
pyibisami/ami/parameter.py
pyibisami/ami/parser.py
pyibisami/ami/reserved_parameter_names.py
pyibisami/ibis/__init__.py
pyibisami/ibis/file.py
pyibisami/ibis/model.py
pyibisami/ibis/parser.py
pyibisami/tools/__init__.py
pyibisami/tools/run_notebook.py
pyibisami/tools/run_tests.py
pyibisami/tools/test_results.xsl
pyibis_ami-8.0.0.dist-info/METADATA
pyibis_ami-8.0.0.dist-info/WHEEL
pyibis_ami-8.0.0.dist-info/entry_points.txt
pyibis_ami-8.0.0.dist-info/top_level.txt
pyibis_ami-8.0.0.dist-info/RECORD
