Metadata-Version: 2.4
Name: pyibis-ami
Version: 8.0.0
Summary: Facilitates working directly with IBIS-AMI DLLs from the Python command prompt.
Author-email: David Banas <capn.freako@gmail.com>
Project-URL: Documentation, https://pyibis-ami.readthedocs.io/en/latest/
Project-URL: Wiki, https://github.com/capn-freako/PyAMI/wiki
Project-URL: GitHub, https://github.com/capn-freako/PyAMI
Project-URL: PyPi, https://pypi.org/project/PyIBIS-AMI/
Keywords: ibis-ami
Classifier: Development Status :: 5 - Production/Stable
Classifier: Environment :: Console
Classifier: Intended Audience :: Developers
Classifier: Operating System :: OS Independent
Classifier: Programming Language :: Python
Classifier: Programming Language :: Python :: 3
Classifier: Programming Language :: Python :: 3.10
Classifier: Programming Language :: Python :: 3.11
Classifier: Programming Language :: Python :: 3.12
Classifier: Programming Language :: Python :: Implementation :: CPython
Classifier: Topic :: System :: Emulators
Classifier: Topic :: Utilities
Requires-Python: <3.13,>=3.10
License-File: LICENSE
Requires-Dist: chaco>=6.0.0
Requires-Dist: click>=8.1.3
Requires-Dist: empy>=3.3.4
Requires-Dist: importlib_resources
Requires-Dist: jupyter
Requires-Dist: matplotlib>=3.6.1
Requires-Dist: numpy<1.27,>=1.26
Requires-Dist: papermill
Requires-Dist: parsec>=3.15
Requires-Dist: scipy>=1.9
Dynamic: license-file
